TOPSIS_Rajeev_101803655-2.0.0.dist-info/METADATA
TOPSIS_Rajeev_101803655-2.0.0.dist-info/RECORD
TOPSIS_Rajeev_101803655-2.0.0.dist-info/WHEEL
TOPSIS_Rajeev_101803655-2.0.0.dist-info/entry_points.txt
TOPSIS_Rajeev_101803655-2.0.0.dist-info/top_level.txt
topsis_101803655/topsis_raj.py
