Metadata-Version: 2.1
Name: TOPSIS-Rajeev-101803655
Version: 2.0.0
Summary: A python package to implement TOPSIS on a given dataset
Home-page: https://github.com/rajeevsingla780/TOPSIS-Rajeev-101803655
Author: RAJEEV SINGLA
Author-email: rsingla1_be18@thapar.edu
License: MIT
Platform: UNKNOWN
Classifier: License :: OSI Approved :: MIT License
Classifier: Programming Language :: Python :: 3
Classifier: Programming Language :: Python :: 3.4
Classifier: Programming Language :: Python :: 3.5
Classifier: Programming Language :: Python :: 3.6
Classifier: Programming Language :: Python :: 3.7
Requires-Dist: pandas
Requires-Dist: numpy
